{"lastUpdated":"4/11/2026","matches":[{"competition_id":"MLS-COM-000001","competition_name":"Major League Soccer - Regular Season","competition_type":"League","end_date":"2026-04-12T00:00:00Z","away_team_id":"MLS-CLU-000007","away_team_name":"FC Cincinnati","home_team_id":"MLS-CLU-00000M","home_team_name":"Toronto FC","home_team_short_name":"Toronto","home_team_three_letter_code":"TOR","away_team_short_name":"Cincinnati","away_team_three_letter_code":"CIN","match_scheduled":true,"match_day":7,"match_day_id":"MLS-DAY-004CBZ","match_id":"MLS-MAT-0009DX","match_type":"MATCHWEEK 7","planned_kickoff_time":"2026-04-11T17:00:00Z","season":2026,"season_id":"MLS-SEA-0001KA","stadium_id":"MLS-STA-00000M","stadium_name":"BMO Field","neutral_venue":false,"start_date":"2026-04-11T00:00:00Z","sub_league":"EASTERN CONFERENCE","date_quality":"","official_information":"","match_date_time_status":"Scheduled","section_name":"TOTAL","competition_label":"MLS Regular Season 2026","series_type":"","competition_name_french":"MLS - Saison régulière","result":"0:0","away_team_goals":0,"home_team_goals":0,"match_status":"scheduled","stadium_city":"Toronto, ON","stadium_country":"Canada"},{"competition_id":"MLS-COM-000001","competition_name":"Major League Soccer - Regular Season","competition_type":"League","end_date":"2026-04-12T00:00:00Z","away_team_id":"MLS-CLU-00000G","away_team_name":"LA Galaxy","home_team_id":"MLS-CLU-000003","home_team_name":"Austin FC","home_team_short_name":"Austin","home_team_three_letter_code":"ATX","away_team_short_name":"LA Galaxy","away_team_three_letter_code":"LA","match_scheduled":true,"match_day":7,"match_day_id":"MLS-DAY-004CBZ","match_id":"MLS-MAT-0009DL","match_type":"MATCHWEEK 7","planned_kickoff_time":"2026-04-11T18:30:00Z","season":2026,"season_id":"MLS-SEA-0001KA","stadium_id":"MLS-STA-000003","stadium_name":"Q2 Stadium","neutral_venue":false,"start_date":"2026-04-11T00:00:00Z","sub_league":"WESTERN CONFERENCE","date_quality":"","official_information":"","match_date_time_status":"Scheduled","section_name":"TOTAL","competition_label":"MLS Regular Season 2026","series_type":"","competition_name_french":"MLS - Saison régulière","result":"0:0","away_team_goals":0,"home_team_goals":0,"match_status":"scheduled","stadium_city":"Austin, TX","stadium_country":"USA"},{"competition_id":"MLS-COM-000001","competition_name":"Major League Soccer - Regular Season","competition_type":"League","end_date":"2026-04-12T00:00:00Z","away_team_id":"MLS-CLU-000002","away_team_name":"Philadelphia Union","home_team_id":"MLS-CLU-000006","home_team_name":"CF Montréal","home_team_short_name":"Montréal","home_team_three_letter_code":"MTL","away_team_short_name":"Philadelphia","away_team_three_letter_code":"PHI","match_scheduled":true,"match_day":7,"match_day_id":"MLS-DAY-004CBZ","match_id":"MLS-MAT-0009DT","match_type":"MATCHWEEK 7","planned_kickoff_time":"2026-04-11T18:30:00Z","season":2026,"season_id":"MLS-SEA-0001KA","stadium_id":"MLS-STA-000006","stadium_name":"Stade Saputo","neutral_venue":false,"start_date":"2026-04-11T00:00:00Z","sub_league":"EASTERN CONFERENCE","date_quality":"","official_information":"","match_date_time_status":"Scheduled","section_name":"TOTAL","competition_label":"MLS Regular Season 2026","series_type":"","competition_name_french":"MLS - Saison régulière","result":"0:0","away_team_goals":0,"home_team_goals":0,"match_status":"scheduled","stadium_city":"Montréal, QC","stadium_country":"Canada"},{"competition_id":"MLS-COM-000001","competition_name":"Major League Soccer - Regular Season","competition_type":"League","end_date":"2026-04-12T00:00:00Z","away_team_id":"MLS-CLU-000001","away_team_name":"Los Angeles Football Club","home_team_id":"MLS-CLU-00000P","home_team_name":"Portland Timbers","home_team_short_name":"Portland","home_team_three_letter_code":"POR","away_team_short_name":"LAFC","away_team_three_letter_code":"LAFC","match_scheduled":true,"match_day":7,"match_day_id":"MLS-DAY-004CBZ","match_id":"MLS-MAT-0009DV","match_type":"MATCHWEEK 7","planned_kickoff_time":"2026-04-11T20:45:00Z","season":2026,"season_id":"MLS-SEA-0001KA","stadium_id":"MLS-STA-00000P","stadium_name":"Providence Park","neutral_venue":false,"start_date":"2026-04-11T00:00:00Z","sub_league":"WESTERN CONFERENCE","date_quality":"","official_information":"","match_date_time_status":"Scheduled","section_name":"TOTAL","competition_label":"MLS Regular Season 2026","series_type":"","competition_name_french":"MLS - Saison régulière","result":"0:0","away_team_goals":0,"home_team_goals":0,"match_status":"scheduled","stadium_city":"Portland, OR","stadium_country":"USA"},{"competition_id":"MLS-COM-000001","competition_name":"Major League Soccer - Regular Season","competition_type":"League","end_date":"2026-04-12T00:00:00Z","away_team_id":"MLS-CLU-000009","away_team_name":"Nashville SC","home_team_id":"MLS-CLU-00000I","home_team_name":"Charlotte FC","home_team_short_name":"Charlotte","home_team_three_letter_code":"CLT","away_team_short_name":"Nashville","away_team_three_letter_code":"NSH","match_scheduled":true,"match_day":7,"match_day_id":"MLS-DAY-004CBZ","match_id":"MLS-MAT-0009DM","match_type":"MATCHWEEK 7","planned_kickoff_time":"2026-04-11T23:30:00Z","season":2026,"season_id":"MLS-SEA-0001KA","stadium_id":"MLS-STA-00000I","stadium_name":"Bank of America Stadium","neutral_venue":false,"start_date":"2026-04-11T00:00:00Z","sub_league":"EASTERN CONFERENCE","date_quality":"","official_information":"","match_date_time_status":"Scheduled","section_name":"TOTAL","competition_label":"MLS Regular Season 2026","series_type":"","competition_name_french":"MLS - Saison régulière","result":"0:0","away_team_goals":0,"home_team_goals":0,"match_status":"scheduled","stadium_city":"Charlotte, NC","stadium_country":"USA"},{"competition_id":"MLS-COM-000001","competition_name":"Major League Soccer - Regular Season","competition_type":"League","end_date":"2026-04-12T00:00:00Z","away_team_id":"MLS-CLU-00000B","away_team_name":"Red Bull New York","home_team_id":"MLS-CLU-000008","home_team_name":"Inter Miami CF","home_team_short_name":"Miami","home_team_three_letter_code":"MIA","away_team_short_name":"New York","away_team_three_letter_code":"RBNY","match_scheduled":true,"match_day":7,"match_day_id":"MLS-DAY-004CBZ","match_id":"MLS-MAT-0009DS","match_type":"MATCHWEEK 7","planned_kickoff_time":"2026-04-11T23:30:00Z","season":2026,"season_id":"MLS-SEA-0001KA","stadium_id":"MLS-STA-000072","stadium_name":"Nu Stadium","neutral_venue":false,"start_date":"2026-04-11T00:00:00Z","sub_league":"EASTERN CONFERENCE","date_quality":"","official_information":"","match_date_time_status":"Scheduled","section_name":"TOTAL","competition_label":"MLS Regular Season 2026","series_type":"","competition_name_french":"MLS - Saison régulière","result":"0:0","away_team_goals":0,"home_team_goals":0,"match_status":"scheduled","stadium_city":"Miami, FL","stadium_country":"USA"},{"competition_id":"MLS-COM-000001","competition_name":"Major League Soccer - Regular Season","competition_type":"League","end_date":"2026-04-12T00:00:00Z","away_team_id":"MLS-CLU-00000D","away_team_name":"D.C. United","home_team_id":"MLS-CLU-00000N","home_team_name":"New England Revolution","home_team_short_name":"New England","home_team_three_letter_code":"NE","away_team_short_name":"D.C. United","away_team_three_letter_code":"DC","match_scheduled":true,"match_day":7,"match_day_id":"MLS-DAY-004CBZ","match_id":"MLS-MAT-0009DU","match_type":"MATCHWEEK 7","planned_kickoff_time":"2026-04-11T23:30:00Z","season":2026,"season_id":"MLS-SEA-0001KA","stadium_id":"MLS-STA-00000N","stadium_name":"Gillette Stadium","neutral_venue":false,"start_date":"2026-04-11T00:00:00Z","sub_league":"EASTERN CONFERENCE","date_quality":"","official_information":"","match_date_time_status":"Scheduled","section_name":"TOTAL","competition_label":"MLS Regular Season 2026","series_type":"","competition_name_french":"MLS - Saison régulière","result":"0:0","away_team_goals":0,"home_team_goals":0,"match_status":"scheduled","stadium_city":"Foxborough, MA","stadium_country":"USA"},{"competition_id":"MLS-COM-000001","competition_name":"Major League Soccer - Regular Season","competition_type":"League","end_date":"2026-04-12T00:00:00Z","away_team_id":"MLS-CLU-000004","away_team_name":"New York City Football Club","home_team_id":"MLS-CLU-00000C","home_team_name":"Vancouver Whitecaps FC","home_team_short_name":"Vancouver","home_team_three_letter_code":"VAN","away_team_short_name":"New York City","away_team_three_letter_code":"NYC","match_scheduled":true,"match_day":7,"match_day_id":"MLS-DAY-004CBZ","match_id":"MLS-MAT-0009DY","match_type":"MATCHWEEK 7","planned_kickoff_time":"2026-04-11T23:30:00Z","season":2026,"season_id":"MLS-SEA-0001KA","stadium_id":"MLS-STA-00000C","stadium_name":"BC Place","neutral_venue":false,"start_date":"2026-04-11T00:00:00Z","date_quality":"","official_information":"","match_date_time_status":"Scheduled","section_name":"TOTAL","competition_label":"MLS Regular Season 2026","series_type":"","competition_name_french":"MLS - Saison régulière","result":"0:0","away_team_goals":0,"home_team_goals":0,"match_status":"scheduled","stadium_city":"Vancouver, BC","stadium_country":"Canada"},{"competition_id":"MLS-COM-000001","competition_name":"Major League Soccer - Regular Season","competition_type":"League","end_date":"2026-04-12T00:00:00Z","away_team_id":"MLS-CLU-00000A","away_team_name":"Atlanta United","home_team_id":"MLS-CLU-00000F","home_team_name":"Chicago Fire FC","home_team_short_name":"Chicago","home_team_three_letter_code":"CHI","away_team_short_name":"Atlanta","away_team_three_letter_code":"ATL","match_scheduled":true,"match_day":7,"match_day_id":"MLS-DAY-004CBZ","match_id":"MLS-MAT-0009DN","match_type":"MATCHWEEK 7","planned_kickoff_time":"2026-04-12T00:30:00Z","season":2026,"season_id":"MLS-SEA-0001KA","stadium_id":"MLS-STA-00000F","stadium_name":"Soldier Field","neutral_venue":false,"start_date":"2026-04-11T00:00:00Z","sub_league":"EASTERN CONFERENCE","date_quality":"","official_information":"","match_date_time_status":"Scheduled","section_name":"TOTAL","competition_label":"MLS Regular Season 2026","series_type":"","competition_name_french":"MLS - Saison régulière","result":"0:0","away_team_goals":0,"home_team_goals":0,"match_status":"scheduled","stadium_city":"Chicago, IL","stadium_country":"USA"},{"competition_id":"MLS-COM-000001","competition_name":"Major League Soccer - Regular Season","competition_type":"League","end_date":"2026-04-12T00:00:00Z","away_team_id":"MLS-CLU-00001L","away_team_name":"St. Louis CITY SC","home_team_id":"MLS-CLU-000005","home_team_name":"FC Dallas","home_team_short_name":"Dallas","home_team_three_letter_code":"DAL","away_team_short_name":"St. Louis","away_team_three_letter_code":"STL","match_scheduled":true,"match_day":7,"match_day_id":"MLS-DAY-004CBZ","match_id":"MLS-MAT-0009DQ","match_type":"MATCHWEEK 7","planned_kickoff_time":"2026-04-12T00:30:00Z","season":2026,"season_id":"MLS-SEA-0001KA","stadium_id":"MLS-STA-000005","stadium_name":"Toyota Stadium","neutral_venue":false,"start_date":"2026-04-11T00:00:00Z","sub_league":"WESTERN CONFERENCE","date_quality":"","official_information":"","match_date_time_status":"Scheduled","section_name":"TOTAL","competition_label":"MLS Regular Season 2026","series_type":"","competition_name_french":"MLS - Saison régulière","result":"0:0","away_team_goals":0,"home_team_goals":0,"match_status":"scheduled","stadium_city":"Frisco, TX","stadium_country":"USA"},{"competition_id":"MLS-COM-000001","competition_name":"Major League Soccer - Regular Season","competition_type":"League","end_date":"2026-04-12T00:00:00Z","away_team_id":"MLS-CLU-00000Q","away_team_name":"San Jose Earthquakes","home_team_id":"MLS-CLU-00000K","home_team_name":"Sporting Kansas City","home_team_short_name":"Kansas City","home_team_three_letter_code":"SKC","away_team_short_name":"San Jose","away_team_three_letter_code":"SJ","match_scheduled":true,"match_day":7,"match_day_id":"MLS-DAY-004CBZ","match_id":"MLS-MAT-0009DR","match_type":"MATCHWEEK 7","planned_kickoff_time":"2026-04-12T00:30:00Z","season":2026,"season_id":"MLS-SEA-0001KA","stadium_id":"MLS-STA-00000K","stadium_name":"Sporting Park","neutral_venue":false,"start_date":"2026-04-11T00:00:00Z","sub_league":"WESTERN CONFERENCE","date_quality":"","official_information":"","match_date_time_status":"Scheduled","section_name":"TOTAL","competition_label":"MLS Regular Season 2026","series_type":"","competition_name_french":"MLS - Saison régulière","result":"0:0","away_team_goals":0,"home_team_goals":0,"match_status":"scheduled","stadium_city":"Kansas City, KS","stadium_country":"USA"},{"competition_id":"MLS-COM-000001","competition_name":"Major League Soccer - Regular Season","competition_type":"League","end_date":"2026-04-12T00:00:00Z","away_team_id":"MLS-CLU-00000H","away_team_name":"Houston Dynamo FC","home_team_id":"MLS-CLU-00000J","home_team_name":"Colorado Rapids","home_team_short_name":"Colorado","home_team_three_letter_code":"COL","away_team_short_name":"Houston","away_team_three_letter_code":"HOU","match_scheduled":true,"match_day":7,"match_day_id":"MLS-DAY-004CBZ","match_id":"MLS-MAT-0009DO","match_type":"MATCHWEEK 7","planned_kickoff_time":"2026-04-12T01:30:00Z","season":2026,"season_id":"MLS-SEA-0001KA","stadium_id":"MLS-STA-00000J","stadium_name":"DICK'S Sporting Goods Park","neutral_venue":false,"start_date":"2026-04-11T00:00:00Z","sub_league":"WESTERN CONFERENCE","date_quality":"","official_information":"","match_date_time_status":"Scheduled","section_name":"TOTAL","competition_label":"MLS Regular Season 2026","series_type":"","competition_name_french":"MLS - Saison régulière","result":"0:0","away_team_goals":0,"home_team_goals":0,"match_status":"scheduled","stadium_city":"Commerce City, CO","stadium_country":"USA"},{"competition_id":"MLS-COM-000001","competition_name":"Major League Soccer - Regular Season","competition_type":"League","end_date":"2026-04-12T00:00:00Z","away_team_id":"MLS-CLU-00000L","away_team_name":"Minnesota United FC","home_team_id":"MLS-CLU-000065","home_team_name":"San Diego FC","home_team_short_name":"San Diego","home_team_three_letter_code":"SD","away_team_short_name":"Minnesota","away_team_three_letter_code":"MIN","match_scheduled":true,"match_day":7,"match_day_id":"MLS-DAY-004CBZ","match_id":"MLS-MAT-0009DW","match_type":"MATCHWEEK 7","planned_kickoff_time":"2026-04-12T02:30:00Z","season":2026,"season_id":"MLS-SEA-0001KA","stadium_id":"MLS-STA-000037","stadium_name":"Snapdragon Stadium","neutral_venue":false,"start_date":"2026-04-11T00:00:00Z","sub_league":"WESTERN CONFERENCE","date_quality":"","official_information":"","match_date_time_status":"Scheduled","section_name":"TOTAL","competition_label":"MLS Regular Season 2026","series_type":"","competition_name_french":"MLS - Saison régulière","result":"0:0","away_team_goals":0,"home_team_goals":0,"match_status":"scheduled","stadium_city":"San Diego","stadium_country":"USA"}]}