{"lastUpdated":"2/28/2026","matches":[{"competition_id":"MLS-COM-000001","competition_name":"Major League Soccer - Regular Season","competition_type":"League","end_date":"2026-03-01T00:00:00Z","away_team_id":"MLS-CLU-000006","away_team_name":"CF Montréal","home_team_id":"MLS-CLU-00000F","home_team_name":"Chicago Fire FC","home_team_short_name":"Chicago","home_team_three_letter_code":"CHI","away_team_short_name":"Montréal","away_team_three_letter_code":"MTL","match_scheduled":true,"match_day":2,"match_day_id":"MLS-DAY-004CBU","match_id":"MLS-MAT-0009BJ","match_type":"MATCHWEEK 2","planned_kickoff_time":"2026-02-28T19:30:00Z","season":2026,"season_id":"MLS-SEA-0001KA","stadium_id":"MLS-STA-00000F","stadium_name":"Soldier Field","neutral_venue":false,"start_date":"2026-02-28T00:00:00Z","sub_league":"EASTERN CONFERENCE","date_quality":"","official_information":"","match_date_time_status":"Scheduled","section_name":"TOTAL","competition_label":"MLS Regular Season 2026","series_type":"","competition_name_french":"MLS - Saison régulière","result":"1:0","away_team_goals":0,"home_team_goals":1,"match_status":"secondHalf","minute_of_play":"88","stadium_city":"Chicago, IL","stadium_country":"USA"},{"competition_id":"MLS-COM-000001","competition_name":"Major League Soccer - Regular Season","competition_type":"League","end_date":"2026-03-01T00:00:00Z","away_team_id":"MLS-CLU-00000N","away_team_name":"New England Revolution","home_team_id":"MLS-CLU-00000B","home_team_name":"Red Bull New York","home_team_short_name":"New York","home_team_three_letter_code":"RBNY","away_team_short_name":"New England","away_team_three_letter_code":"NE","match_scheduled":true,"match_day":2,"match_day_id":"MLS-DAY-004CBU","match_id":"MLS-MAT-0009BQ","match_type":"MATCHWEEK 2","planned_kickoff_time":"2026-02-28T19:30:00Z","season":2026,"season_id":"MLS-SEA-0001KA","stadium_id":"MLS-STA-00000B","stadium_name":"Sports Illustrated Stadium","neutral_venue":false,"start_date":"2026-02-28T00:00:00Z","sub_league":"EASTERN CONFERENCE","date_quality":"","official_information":"","match_date_time_status":"Scheduled","section_name":"TOTAL","competition_label":"MLS Regular Season 2026","series_type":"","competition_name_french":"MLS - Saison régulière","result":"1:0","away_team_goals":0,"home_team_goals":1,"match_status":"secondHalf","minute_of_play":"89","stadium_city":"Harrison, NJ","stadium_country":"USA"},{"competition_id":"MLS-COM-000001","competition_name":"Major League Soccer - Regular Season","competition_type":"League","end_date":"2026-03-01T00:00:00Z","away_team_id":"MLS-CLU-00000P","away_team_name":"Portland Timbers","home_team_id":"MLS-CLU-00000J","home_team_name":"Colorado Rapids","home_team_short_name":"Colorado","home_team_three_letter_code":"COL","away_team_short_name":"Portland","away_team_three_letter_code":"POR","match_scheduled":true,"match_day":2,"match_day_id":"MLS-DAY-004CBU","match_id":"MLS-MAT-0009BK","match_type":"MATCHWEEK 2","planned_kickoff_time":"2026-02-28T21:30:00Z","season":2026,"season_id":"MLS-SEA-0001KA","stadium_id":"MLS-STA-00000J","stadium_name":"DICK'S Sporting Goods Park","neutral_venue":false,"start_date":"2026-02-28T00:00:00Z","sub_league":"WESTERN CONFERENCE","date_quality":"","official_information":"","match_date_time_status":"Scheduled","section_name":"TOTAL","competition_label":"MLS Regular Season 2026","series_type":"","competition_name_french":"MLS - Saison régulière","result":"0:0","away_team_goals":0,"home_team_goals":0,"match_status":"scheduled","stadium_city":"Commerce City, CO","stadium_country":"USA"},{"competition_id":"MLS-COM-000001","competition_name":"Major League Soccer - Regular Season","competition_type":"League","end_date":"2026-03-01T00:00:00Z","away_team_id":"MLS-CLU-000007","away_team_name":"FC Cincinnati","home_team_id":"MLS-CLU-00000L","home_team_name":"Minnesota United FC","home_team_short_name":"Minnesota","home_team_three_letter_code":"MIN","away_team_short_name":"Cincinnati","away_team_three_letter_code":"CIN","match_scheduled":true,"match_day":2,"match_day_id":"MLS-DAY-004CBU","match_id":"MLS-MAT-0009BP","match_type":"MATCHWEEK 2","planned_kickoff_time":"2026-02-28T21:30:00Z","season":2026,"season_id":"MLS-SEA-0001KA","stadium_id":"MLS-STA-00000L","stadium_name":"Allianz Field","neutral_venue":false,"start_date":"2026-02-28T00:00:00Z","date_quality":"","official_information":"","match_date_time_status":"Scheduled","section_name":"TOTAL","competition_label":"MLS Regular Season 2026","series_type":"","competition_name_french":"MLS - Saison régulière","result":"0:0","away_team_goals":0,"home_team_goals":0,"match_status":"scheduled","stadium_city":"St. Paul, MN","stadium_country":"USA"},{"competition_id":"MLS-COM-000001","competition_name":"Major League Soccer - Regular Season","competition_type":"League","end_date":"2026-03-01T00:00:00Z","away_team_id":"MLS-CLU-00000S","away_team_name":"Seattle Sounders FC","home_team_id":"MLS-CLU-00000R","home_team_name":"Real Salt Lake","home_team_short_name":"Salt Lake","home_team_three_letter_code":"RSL","away_team_short_name":"Seattle","away_team_three_letter_code":"SEA","match_scheduled":true,"match_day":2,"match_day_id":"MLS-DAY-004CBU","match_id":"MLS-MAT-0009BR","match_type":"MATCHWEEK 2","planned_kickoff_time":"2026-03-01T00:30:00Z","season":2026,"season_id":"MLS-SEA-0001KA","stadium_id":"MLS-STA-00000R","stadium_name":"America First Field","neutral_venue":false,"start_date":"2026-02-28T00:00:00Z","sub_league":"WESTERN CONFERENCE","date_quality":"","official_information":"","match_date_time_status":"Scheduled","section_name":"TOTAL","competition_label":"MLS Regular Season 2026","series_type":"","competition_name_french":"MLS - Saison régulière","result":"0:0","away_team_goals":0,"home_team_goals":0,"match_status":"scheduled","stadium_city":"Sandy, UT","stadium_country":"USA"},{"competition_id":"MLS-COM-000001","competition_name":"Major League Soccer - Regular Season","competition_type":"League","end_date":"2026-03-01T00:00:00Z","away_team_id":"MLS-CLU-00000A","away_team_name":"Atlanta United","home_team_id":"MLS-CLU-00000Q","home_team_name":"San Jose Earthquakes","home_team_short_name":"San Jose","home_team_three_letter_code":"SJ","away_team_short_name":"Atlanta","away_team_three_letter_code":"ATL","match_scheduled":true,"match_day":2,"match_day_id":"MLS-DAY-004CBU","match_id":"MLS-MAT-0009BS","match_type":"MATCHWEEK 2","planned_kickoff_time":"2026-03-01T00:30:00Z","season":2026,"season_id":"MLS-SEA-0001KA","stadium_id":"MLS-STA-00000Q","stadium_name":"PayPal Park","neutral_venue":false,"start_date":"2026-02-28T00:00:00Z","date_quality":"","official_information":"","match_date_time_status":"Scheduled","section_name":"TOTAL","competition_label":"MLS Regular Season 2026","series_type":"","competition_name_french":"MLS - Saison régulière","result":"0:0","away_team_goals":0,"home_team_goals":0,"match_status":"scheduled","stadium_city":"San Jose, CA","stadium_country":"USA"},{"competition_id":"MLS-COM-000001","competition_name":"Major League Soccer - Regular Season","competition_type":"League","end_date":"2026-03-01T00:00:00Z","away_team_id":"MLS-CLU-000009","away_team_name":"Nashville SC","home_team_id":"MLS-CLU-000005","home_team_name":"FC Dallas","home_team_short_name":"Dallas","home_team_three_letter_code":"DAL","away_team_short_name":"Nashville","away_team_three_letter_code":"NSH","match_scheduled":true,"match_day":2,"match_day_id":"MLS-DAY-004CBU","match_id":"MLS-MAT-0009BL","match_type":"MATCHWEEK 2","planned_kickoff_time":"2026-03-01T01:30:00Z","season":2026,"season_id":"MLS-SEA-0001KA","stadium_id":"MLS-STA-000005","stadium_name":"Toyota Stadium","neutral_venue":false,"start_date":"2026-02-28T00:00:00Z","date_quality":"","official_information":"","match_date_time_status":"Scheduled","section_name":"TOTAL","competition_label":"MLS Regular Season 2026","series_type":"","competition_name_french":"MLS - Saison régulière","result":"0:0","away_team_goals":0,"home_team_goals":0,"match_status":"scheduled","stadium_city":"Frisco, TX","stadium_country":"USA"},{"competition_id":"MLS-COM-000001","competition_name":"Major League Soccer - Regular Season","competition_type":"League","end_date":"2026-03-01T00:00:00Z","away_team_id":"MLS-CLU-000001","away_team_name":"Los Angeles Football Club","home_team_id":"MLS-CLU-00000H","home_team_name":"Houston Dynamo FC","home_team_short_name":"Houston","home_team_three_letter_code":"HOU","away_team_short_name":"LAFC","away_team_three_letter_code":"LAFC","match_scheduled":true,"match_day":2,"match_day_id":"MLS-DAY-004CBU","match_id":"MLS-MAT-0009BM","match_type":"MATCHWEEK 2","planned_kickoff_time":"2026-03-01T01:30:00Z","season":2026,"season_id":"MLS-SEA-0001KA","stadium_id":"MLS-STA-00000H","stadium_name":"Shell Energy Stadium","neutral_venue":false,"start_date":"2026-02-28T00:00:00Z","sub_league":"WESTERN CONFERENCE","date_quality":"","official_information":"","match_date_time_status":"Scheduled","section_name":"TOTAL","competition_label":"MLS Regular Season 2026","series_type":"","competition_name_french":"MLS - Saison régulière","result":"0:0","away_team_goals":0,"home_team_goals":0,"match_status":"scheduled","stadium_city":"Houston, TX","stadium_country":"USA"},{"competition_id":"MLS-COM-000001","competition_name":"Major League Soccer - Regular Season","competition_type":"League","end_date":"2026-03-01T00:00:00Z","away_team_id":"MLS-CLU-00000E","away_team_name":"Columbus Crew","home_team_id":"MLS-CLU-00000K","home_team_name":"Sporting Kansas City","home_team_short_name":"Kansas City","home_team_three_letter_code":"SKC","away_team_short_name":"Columbus","away_team_three_letter_code":"CLB","match_scheduled":true,"match_day":2,"match_day_id":"MLS-DAY-004CBU","match_id":"MLS-MAT-0009BN","match_type":"MATCHWEEK 2","planned_kickoff_time":"2026-03-01T01:30:00Z","season":2026,"season_id":"MLS-SEA-0001KA","stadium_id":"MLS-STA-00000K","stadium_name":"Sporting Park","neutral_venue":false,"start_date":"2026-02-28T00:00:00Z","date_quality":"","official_information":"","match_date_time_status":"Scheduled","section_name":"TOTAL","competition_label":"MLS Regular Season 2026","series_type":"","competition_name_french":"MLS - Saison régulière","result":"0:0","away_team_goals":0,"home_team_goals":0,"match_status":"scheduled","stadium_city":"Kansas City, KS","stadium_country":"USA"},{"competition_id":"MLS-COM-000001","competition_name":"Major League Soccer - Regular Season","competition_type":"League","end_date":"2026-03-01T00:00:00Z","away_team_id":"MLS-CLU-00000M","away_team_name":"Toronto FC","home_team_id":"MLS-CLU-00000C","home_team_name":"Vancouver Whitecaps FC","home_team_short_name":"Vancouver","home_team_three_letter_code":"VAN","away_team_short_name":"Toronto","away_team_three_letter_code":"TOR","match_scheduled":true,"match_day":2,"match_day_id":"MLS-DAY-004CBU","match_id":"MLS-MAT-0009BT","match_type":"MATCHWEEK 2","planned_kickoff_time":"2026-03-01T02:30:00Z","season":2026,"season_id":"MLS-SEA-0001KA","stadium_id":"MLS-STA-00000C","stadium_name":"BC Place","neutral_venue":false,"start_date":"2026-02-28T00:00:00Z","date_quality":"","official_information":"","match_date_time_status":"Scheduled","section_name":"TOTAL","competition_label":"MLS Regular Season 2026","series_type":"","competition_name_french":"MLS - Saison régulière","result":"0:0","away_team_goals":0,"home_team_goals":0,"match_status":"scheduled","stadium_city":"Vancouver, BC","stadium_country":"Canada"},{"competition_id":"MLS-COM-000001","competition_name":"Major League Soccer - Regular Season","competition_type":"League","end_date":"2026-03-01T00:00:00Z","away_team_id":"MLS-CLU-00000I","away_team_name":"Charlotte FC","home_team_id":"MLS-CLU-00000G","home_team_name":"LA Galaxy","home_team_short_name":"LA Galaxy","home_team_three_letter_code":"LA","away_team_short_name":"Charlotte","away_team_three_letter_code":"CLT","match_scheduled":true,"match_day":2,"match_day_id":"MLS-DAY-004CBU","match_id":"MLS-MAT-0009BO","match_type":"MATCHWEEK 2","planned_kickoff_time":"2026-03-01T03:30:00Z","season":2026,"season_id":"MLS-SEA-0001KA","stadium_id":"MLS-STA-00000G","stadium_name":"Dignity Health Sports Park","neutral_venue":false,"start_date":"2026-02-28T00:00:00Z","date_quality":"","official_information":"","match_date_time_status":"Scheduled","section_name":"TOTAL","competition_label":"MLS Regular Season 2026","series_type":"","competition_name_french":"MLS - Saison régulière","result":"0:0","away_team_goals":0,"home_team_goals":0,"match_status":"scheduled","stadium_city":"Carson, CA","stadium_country":"USA"}]}